featureswitches/__init__.py
featureswitches/cache_factory.py
featureswitches/errors.py
featureswitches/feature.py
featureswitches/featureswitches.py
featureswitches/http.py
featureswitches/version.py
featureswitches-0.8.6.dist-info/DESCRIPTION.rst
featureswitches-0.8.6.dist-info/METADATA
featureswitches-0.8.6.dist-info/RECORD
featureswitches-0.8.6.dist-info/WHEEL
featureswitches-0.8.6.dist-info/metadata.json
featureswitches-0.8.6.dist-info/top_level.txt
