Metadata-Version: 2.0
Name: featureswitches
Version: 0.8.6
Summary: Python client for FeatureSwitches.com
Home-page: https://featureswitches.com
Author: Joel Weirauch
Author-email: joel@featureswitches.com
License: UNKNOWN
Platform: UNKNOWN
Classifier: Development Status :: 5 - Production/Stable
Classifier: Intended Audience :: Developers
Classifier: License :: OSI Approved :: MIT License
Classifier: Operating System :: OS Independent
Classifier: Programming Language :: Python
Classifier: Programming Language :: Python :: 2
Classifier: Programming Language :: Python :: 2.6
Classifier: Programming Language :: Python :: 2.7
Classifier: Programming Language :: Python :: 3
Classifier: Programming Language :: Python :: 3.2
Classifier: Programming Language :: Python :: 3.3
Classifier: Programming Language :: Python :: Implementation :: PyPy
Classifier: Topic :: Software Development :: Libraries :: Python Modules
Requires-Dist: dogpile.cache (>=0.5.7)
Requires-Dist: requests (>=2.9.1)
Requires-Dist: simplejson
